django_pre_commit_hooks/__init__.py
django_pre_commit_hooks/compile_messages.py
django_pre_commit_hooks/py.typed
django_pre_commit_hooks-1.1.0.dist-info/licenses/LICENSE
django_pre_commit_hooks-1.1.0.dist-info/METADATA
django_pre_commit_hooks-1.1.0.dist-info/WHEEL
django_pre_commit_hooks-1.1.0.dist-info/entry_points.txt
django_pre_commit_hooks-1.1.0.dist-info/top_level.txt
django_pre_commit_hooks-1.1.0.dist-info/RECORD
