Metadata-Version: 2.4
Name: django-pre-commit-hooks
Version: 1.1.0
Summary: A collection of pre-commit hooks for Django projects
Author-email: Bruno Alla <oss@browniebroke.com>
License-Expression: MIT
Project-URL: Bug Tracker, https://github.com/browniebroke/django-pre-commit-hooks/issues
Project-URL: Changelog, https://github.com/browniebroke/django-pre-commit-hooks/blob/main/CHANGELOG.md
Project-URL: repository, https://github.com/browniebroke/django-pre-commit-hooks
Classifier: Development Status :: 2 - Pre-Alpha
Classifier: Intended Audience :: Developers
Classifier: Natural Language :: English
Classifier: Operating System :: OS Independent
Classifier: Programming Language :: Python :: 3.10
Classifier: Programming Language :: Python :: 3.11
Classifier: Programming Language :: Python :: 3.12
Classifier: Programming Language :: Python :: 3.13
Classifier: Programming Language :: Python :: 3.14
Classifier: Topic :: Software Development :: Libraries
Requires-Python: >=3.10
License-File: LICENSE
Requires-Dist: django
Dynamic: license-file
